{
  "runtimeOptions": {
    "tfm": "netcoreapp3.1",
    "frameworks": [
      {
        "name": "Microsoft.WindowsDesktop.App",
        "version": "3.1.0"
      },
      {
        "name": "Microsoft.AspNetCore.App",
        "version": "3.1.0"
      }
    ],
    "additionalProbingPaths": [
      "C:\\Users\\admin\\.dotnet\\store\\|arch|\\|tfm|",
      "C:\\Users\\admin\\.nuget\\packages",
      "C:\\Microsoft\\Xamarin\\NuGet",
      "C:\\Program Files\\dotnet\\sdk\\NuGetFallbackFolder"
    ],
    "configProperties": {
      "Microsoft.NETCore.DotNetHostPolicy.SetAppPaths": true
    }
  }
}